quickatetools/__init__.py
quickatetools/clipboard_matrix.py
quickatetools/commands.py
quickatetools/template_feature.py
QuickATETools-1.0.1.dist-info/METADATA
QuickATETools-1.0.1.dist-info/WHEEL
QuickATETools-1.0.1.dist-info/entry_points.txt
QuickATETools-1.0.1.dist-info/top_level.txt
QuickATETools-1.0.1.dist-info/RECORD
